README.md
setup.py
boilermaker/PlatformDef.py
boilermaker/ProjectDef.py
boilermaker/__init__.py
boilermaker/__main__.py
boilermaker/ansi.py
boilermaker/boma.py
boilermaker/loader.py
boilermaker.egg-info/PKG-INFO
boilermaker.egg-info/SOURCES.txt
boilermaker.egg-info/dependency_links.txt
boilermaker.egg-info/requires.txt
boilermaker.egg-info/top_level.txt