Metadata-Version: 2.1
Name: boilermaker
Version: 0.0.1
Summary: A C++ code generator that transforms a declarative description into static types.
Home-page: https://github.com/spacemeat/boilermaker
Author: Trevor Schrock
Author-email: spacemeat@gmail.com
License: UNKNOWN
Platform: UNKNOWN
Classifier: Programming Language :: Python :: 3
Classifier: License :: OSI Approved :: MIT License
Classifier: Operating System :: POSIX :: Linux
Classifier: Programming Language :: C++
Classifier: Topic :: Software Development :: Code Generators
Requires-Python: >=3.8
Provides-Extra: dev
